inuyasha/__init__.py
inuyasha/case.py
inuyasha/cli.py
inuyasha/config.py
inuyasha/scaffold.py
inuyasha/driver/__init__.py
inuyasha/driver/api.py
inuyasha/driver/web.py
inuyasha/test_project/api_test/__init__.py
inuyasha/test_project/api_test/test_application/__init__.py
inuyasha/test_project/api_test/test_application/http/__init__.py
inuyasha/test_project/api_test/test_application/http/template/__init__.py
inuyasha/test_project/api_test/test_application/http/template/body.py
inuyasha/test_project/api_test/test_application/http/template/header.py
inuyasha/test_project/api_test/test_application/http/template/interface.py
inuyasha/test_project/api_test/test_application/http/template/url.py
inuyasha/test_project/api_test/test_application/http/test_case/__init__.py
inuyasha/test_project/api_test/test_application/http/test_case/busi.py
inuyasha/test_project/api_test/test_application/http/test_case/flow.py
inuyasha/test_project/api_test/test_application/http/test_case/interface.py
inuyasha/test_project/api_test/test_application/http/test_case/prod.py
inuyasha/test_project/api_test/test_application/http/test_data/__init__.py
inuyasha/test_project/api_test/test_application/http/test_data/busi.py
inuyasha/test_project/api_test/test_application/http/test_data/flow.py
inuyasha/test_project/api_test/test_application/http/test_data/interface.py
inuyasha/test_project/api_test/test_application/http/test_data/prod.py
inuyasha/test_project/ui_test/__init__.py
inuyasha/test_project/ui_test/test_application/__init__.py
inuyasha/test_project/ui_test/test_application/locators/__init__.py
inuyasha/test_project/ui_test/test_application/locators/test_locators.py
inuyasha/test_project/ui_test/test_application/page_objects/__init__.py
inuyasha/test_project/ui_test/test_application/page_objects/test_po.py
inuyasha/test_project/ui_test/test_application/test_cases/__init__.py
inuyasha/test_project/ui_test/test_application/test_cases/busi.py
inuyasha-0.3.0.dist-info/LICENSE
inuyasha-0.3.0.dist-info/METADATA
inuyasha-0.3.0.dist-info/WHEEL
inuyasha-0.3.0.dist-info/entry_points.txt
inuyasha-0.3.0.dist-info/top_level.txt
inuyasha-0.3.0.dist-info/RECORD
