Metadata-Version: 2.1
Name: inuyasha
Version: 0.3.0
Summary: automation testing framework based on Pytest
Home-page: https://github.com/jaylu2018/miku/tree/main
Author: luyh
Author-email: 2806767301@qq.com
License: Apache License 2.0
Platform: UNKNOWN
Classifier: Intended Audience :: Developers
Classifier: Operating System :: MacOS :: MacOS X
Classifier: Operating System :: Microsoft :: Windows
Classifier: Programming Language :: Python
Classifier: Programming Language :: Python :: 3.7
Classifier: Programming Language :: Python :: 3.8
Classifier: Programming Language :: Python :: 3.9
License-File: LICENSE
Requires-Dist: playwright (~=1.30.0)
Requires-Dist: pytest-playwright (~=0.3.0)
Requires-Dist: requests (~=2.28.2)
Requires-Dist: pytest-cases (~=3.6.13)
